anipie/__init__.py
anipie/queries.py
anipie/search_by_query.py
anipie-0.0.10.dist-info/LICENSE
anipie-0.0.10.dist-info/METADATA
anipie-0.0.10.dist-info/WHEEL
anipie-0.0.10.dist-info/top_level.txt
anipie-0.0.10.dist-info/RECORD
