Metadata-Version: 2.1
Name: anipie
Version: 0.0.10
Summary: a simple python wrapper for the Anilist API
Home-page: https://github.com/aritsulynn/anipie
Author: Aritsu
Author-email: lynniswaifu@gmail.com
Classifier: Programming Language :: Python :: 3
Classifier: License :: OSI Approved :: MIT License
Classifier: Operating System :: OS Independent
Requires-Python: >=3.8
License-File: LICENSE
Requires-Dist: requests
